client/__init__.py
client/client.py
quentryanalytics/__init__.py
quentryanalytics/__main__.py
quentryanalytics/client.py
quentryanalytics/dicom.py
quentryanalytics/runtime.py
quentryanalytics-0.1.10.dist-info/METADATA
quentryanalytics-0.1.10.dist-info/WHEEL
quentryanalytics-0.1.10.dist-info/entry_points.txt
quentryanalytics-0.1.10.dist-info/top_level.txt
quentryanalytics-0.1.10.dist-info/RECORD
